leuvenmapmatching/__init__.py
leuvenmapmatching/map.py
leuvenmapmatching/matching.py
leuvenmapmatching/matching_distance.py
leuvenmapmatching/util.py
leuvenmapmatching/visualization.py
leuvenmapmatching/map/__init__.py
leuvenmapmatching/map/base.py
leuvenmapmatching/map/inmem.py
leuvenmapmatching/map/osmnx.py
leuvenmapmatching/map/sqlite.py
leuvenmapmatching/matcher/__init__.py
leuvenmapmatching/matcher/base.py
leuvenmapmatching/matcher/distance.py
leuvenmapmatching/matcher/newsonkrumm.py
leuvenmapmatching/matcher/simple.py
leuvenmapmatching/util/__init__.py
leuvenmapmatching/util/debug.py
leuvenmapmatching/util/dist_euclidean.py
leuvenmapmatching/util/dist_latlon.py
leuvenmapmatching/util/dist_latlon_nvector.py
leuvenmapmatching/util/evaluation.py
leuvenmapmatching/util/gpx.py
leuvenmapmatching/util/kalman.py
leuvenmapmatching/util/openstreetmap.py
leuvenmapmatching/util/projections.py
leuvenmapmatching/util/segment.py
leuvenmapmatching-1.1.4.dist-info/LICENSE
leuvenmapmatching-1.1.4.dist-info/METADATA
leuvenmapmatching-1.1.4.dist-info/WHEEL
leuvenmapmatching-1.1.4.dist-info/top_level.txt
leuvenmapmatching-1.1.4.dist-info/RECORD
