Metadata-Version: 2.1
Name: leuvenmapmatching
Version: 1.1.4
Summary: Match a trace of GPS positions to a locations and streets on a map
Home-page: https://github.com/wannesm/LeuvenMapMatching
Author: Wannes Meert
Author-email: wannes.meert@cs.kuleuven.be
License: Apache 2.0
Project-URL: Bug Tracker, https://github.com/wannesm/LeuvenMapMatching/issues
Keywords: map matching
Classifier: Intended Audience :: Developers
Classifier: License :: OSI Approved :: Apache Software License
Classifier: Programming Language :: Python :: 3
Requires-Python: >=3.6
License-File: LICENSE
Requires-Dist: numpy
Requires-Dist: scipy
Provides-Extra: all
Requires-Dist: requests ; extra == 'all'
Requires-Dist: smopy ; extra == 'all'
Requires-Dist: matplotlib (>=2.0.0) ; extra == 'all'
Requires-Dist: rtree ; extra == 'all'
Requires-Dist: pyproj ; extra == 'all'
Requires-Dist: nvector (==0.5.2) ; extra == 'all'
Requires-Dist: gpxpy ; extra == 'all'
Requires-Dist: pykalman ; extra == 'all'
Requires-Dist: pytest ; extra == 'all'
Requires-Dist: pytest-runner ; extra == 'all'
Requires-Dist: osmread ; extra == 'all'
Requires-Dist: osmnx ; extra == 'all'
Provides-Extra: db
Requires-Dist: rtree ; extra == 'db'
Requires-Dist: pyproj ; extra == 'db'
Provides-Extra: vis
Requires-Dist: smopy ; extra == 'vis'
Requires-Dist: matplotlib (>=2.0.0) ; extra == 'vis'
